zrx/__init__.py
zrx-0.0.2.dist-info/METADATA
zrx-0.0.2.dist-info/WHEEL
zrx-0.0.2.dist-info/RECORD
