Metadata-Version: 2.4
Name: zrx
Version: 0.0.2
Summary: Zen Reactive Extensions
Project-URL: Source, https://github.com/zensical/zrx
License: MIT
